automata
setup.cfg
setup.py
automata/__init__.py
automata/language.py
automatapython.egg-info/PKG-INFO
automatapython.egg-info/SOURCES.txt
automatapython.egg-info/dependency_links.txt
automatapython.egg-info/top_level.txt