Metadata-Version: 1.0
Name: automatapython
Version: 0.0.5
Summary: The only automaton library you will ever need
Home-page: https://github.com/hemangsk/automatapython
Author: Hemang Kumar
Author-email: hemangsk@gmail.com
License: GPLv3
Keywords: language finite automata turing machine push down automata linear bound automata
Platform: UNKNOWN
